MANIFEST.in
README.md
setup.py
biowardrobe_airflow_analysis/__init__.py
biowardrobe_airflow_analysis/biowardrobe_init.py
biowardrobe_airflow_analysis/biowardrobe_workflows.py
biowardrobe_airflow_analysis.egg-info/PKG-INFO
biowardrobe_airflow_analysis.egg-info/SOURCES.txt
biowardrobe_airflow_analysis.egg-info/dependency_links.txt
biowardrobe_airflow_analysis.egg-info/entry_points.txt
biowardrobe_airflow_analysis.egg-info/not-zip-safe
biowardrobe_airflow_analysis.egg-info/requires.txt
biowardrobe_airflow_analysis.egg-info/top_level.txt
biowardrobe_airflow_analysis/biowardrobe/Settings.py
biowardrobe_airflow_analysis/biowardrobe/__init__.py
biowardrobe_airflow_analysis/biowardrobe/analysis.py
biowardrobe_airflow_analysis/biowardrobe/biow_exceptions.py
biowardrobe_airflow_analysis/biowardrobe/constants.py
biowardrobe_airflow_analysis/biowardrobe/db_uploader.py
biowardrobe_airflow_analysis/biowardrobe/download.py
biowardrobe_airflow_analysis/biowardrobe/force_run.py
biowardrobe_airflow_analysis/biowardrobe/utils.py
biowardrobe_airflow_analysis/operators/__init__.py
biowardrobe_airflow_analysis/operators/biowardrobejobdispatcher.py
biowardrobe_airflow_analysis/operators/biowardrobejobgatherer.py
biowardrobe_airflow_analysis/operators/biowardrobetriggers.py
biowardrobe_airflow_analysis/patch/__init__.py
biowardrobe_airflow_analysis/patch/idx_patch.py
biowardrobe_airflow_analysis/sql_patch/biowardrobe_tables/experimenttype_alter.sql
biowardrobe_airflow_analysis/sql_patch/biowardrobe_tables/experimenttype_drop.sql
biowardrobe_airflow_analysis/sql_patch/biowardrobe_tables/experimenttype_patch.sql
biowardrobe_airflow_analysis/sql_patch/biowardrobe_tables/labdata_alter.sql
biowardrobe_airflow_analysis/sql_patch/biowardrobe_views/dm3_view_patch.sql
biowardrobe_airflow_analysis/sql_patch/biowardrobe_views/hg19_view_patch.sql
biowardrobe_airflow_analysis/sql_patch/biowardrobe_views/mm10_view_patch.sql
biowardrobe_airflow_analysis/sql_patch/biowardrobe_views/rheMac8_view_patch.sql
biowardrobe_airflow_analysis/sql_patch/biowardrobe_views/rn5_view_patch.sql
biowardrobe_airflow_analysis/sql_patch/biowardrobe_views/xenLae9_view_patch.sql
biowardrobe_airflow_analysis/sql_patch/biowardrobe_views/xenTro3_view_patch.sql
biowardrobe_airflow_analysis/sql_patch/biowardrobe_views/xenTro7_1_view_patch.sql
